{
  "project_info": {
    "project_number": "143155355539",
    "project_id": "leadership-30b55",
    "storage_bucket": "leadership-30b55.firebasestorage.app"
  },
  "client": [
    {
      "client_info": {
        "mobilesdk_app_id": "1:143155355539:android:87d8f512b078a5c9dd5266",
        "android_client_info": {
          "package_name": "com.example.leadershipFactory"
        }
      },
      "oauth_client": [],
      "api_key": [
        {
          "current_key": "AIzaSyBw34oQNpKo9cFjCXDx-sl2M_LWLlGZL5A"
        }
      ],
      "services": {
        "appinvite_service": {
          "other_platform_oauth_client": []
        }
      }
    }
  ],
  "configuration_version": "1"
}